LICENSE
MANIFEST.in
README.md
pyproject.toml
setup.py
pefselab/__init__.py
pefselab/__main__.py
pefselab/build_suc.py
pefselab/build_suc_ne.py
pefselab/build_udt.py
pefselab/build_udt_suc_sv.py
pefselab/configuration.py
pefselab/conll.py
pefselab/fasthash.c
pefselab/form.py
pefselab/lemmatize.c
pefselab/lemmatize.pyx
pefselab/options.py
pefselab/swe_pipeline.py
pefselab/tagger.py
pefselab/taglexicon.py
pefselab/tagset.py
pefselab/tokenizer.py
pefselab/tools.py
pefselab/train_swe_pipeline.py
pefselab/train_udt.py
pefselab/translation.py
pefselab/wclexicon.py
pefselab/wrappers.py
pefselab.egg-info/PKG-INFO
pefselab.egg-info/SOURCES.txt
pefselab.egg-info/dependency_links.txt
pefselab.egg-info/requires.txt
pefselab.egg-info/top_level.txt
pefselab/c/hash.c
pefselab/c/headers.h
pefselab/c/main.c
pefselab/c/pytagger.c
pefselab/c/run.c
pefselab/c/search.c
pefselab/c/seq.c
pefselab/c/tag.c
pefselab/c/train.c
pefselab/data/convert-ud-tab.sh
pefselab/data/en-brown320.txt
pefselab/data/sv-ud-dev.tab
pefselab/data/sv-ud-train.tab
pefselab/data/swe-pipeline-ud2.tar.gz
pefselab/data/udt-en-dev.tab
pefselab/data/udt-en-test.tab
pefselab/data/udt-en-train.tab
tests/test_conll.py
tests/test_lemmatizer.py
tests/test_pipeline.py