Metadata-Version: 2.1
Name: pefselab
Version: 0.0.2
Summary: Packaged efselab
Author-email: skogsgren <6107181+skogsgren@users.noreply.github.com>
Project-URL: Homepage, https://github.com/skogsgren/pefselab
Project-URL: Issues, https://github.com/skogsgren/pefselab/issues
Classifier: Programming Language :: Python :: 3
Classifier: License :: OSI Approved :: MIT License
Classifier: Operating System :: OS Independent
Requires-Python: >=3.10
License-File: LICENSE
Requires-Dist: cython<3.0,>=0.25
Requires-Dist: requests
Requires-Dist: dataclasses
